roulette_selector.py
roulette_selector-0.0.1.dist-info/LICENSE.txt
roulette_selector-0.0.1.dist-info/METADATA
roulette_selector-0.0.1.dist-info/WHEEL
roulette_selector-0.0.1.dist-info/top_level.txt
roulette_selector-0.0.1.dist-info/RECORD
