Metadata-Version: 2.1
Name: roulette-selector
Version: 0.0.1
Summary: A small roulette-style random selector of weighted options
Home-page: https://bitbucket.org/Eric-Musa/roulette/
Author: Eric Musa
Author-email: eric.musa17@gmail.com
License: UNKNOWN
Platform: UNKNOWN
Classifier: Programming Language :: Python :: 3
Classifier: License :: OSI Approved :: MIT License
Classifier: Operating System :: OS Independent
Requires-Python: >=3.6
